bigan_pricing/__init__.py
bigan_pricing/pricing.py
bigan_pricing-0.0.0.dist-info/METADATA
bigan_pricing-0.0.0.dist-info/WHEEL
bigan_pricing-0.0.0.dist-info/top_level.txt
bigan_pricing-0.0.0.dist-info/RECORD
